tutti_client/__init__.py
tutti_client/controller.py
tutti_client/error.py
tutti_client/listener.py
tutti_client/tutti.py
tutti_client-0.3.8.dist-info/LICENSE.txt
tutti_client-0.3.8.dist-info/METADATA
tutti_client-0.3.8.dist-info/WHEEL
tutti_client-0.3.8.dist-info/top_level.txt
tutti_client-0.3.8.dist-info/RECORD
