Metadata-Version: 2.1
Name: tutti-client
Version: 0.3.8
Summary: Python client library for Tutti.ai
Home-page: https://github.com/iflb/tutti-client-python
Author: Intelligent Framework Lab
Author-email: saito@iflab.tokyo
Project-URL: Project Owner, http://www.pcl.cs.waseda.ac.jp/
Project-URL: Funding, https://www.waseda.jp/inst/gcs/news/2019/11/29/870/
Keywords: crowdsourcing annotation framework asyncio
Classifier: Development Status :: 2 - Pre-Alpha
Classifier: Intended Audience :: Developers
Classifier: Framework :: AsyncIO
Classifier: License :: OSI Approved :: MIT License
Classifier: Programming Language :: Python :: 3
Classifier: Operating System :: OS Independent
Requires-Python: >=3.6
License-File: LICENSE.txt
Requires-Dist: ducts-client (==0.0.5)
